aiohue/__init__.py
aiohue/discovery.py
aiohue/errors.py
aiohue/util.py
aiohue/v1/__init__.py
aiohue/v1/api.py
aiohue/v1/config.py
aiohue/v1/groups.py
aiohue/v1/lights.py
aiohue/v1/scenes.py
aiohue/v1/sensors.py
aiohue/v2/__init__.py
aiohue/v2/controllers/__init__.py
aiohue/v2/controllers/base.py
aiohue/v2/controllers/config.py
aiohue/v2/controllers/devices.py
aiohue/v2/controllers/events.py
aiohue/v2/controllers/groups.py
aiohue/v2/controllers/lights.py
aiohue/v2/controllers/scenes.py
aiohue/v2/controllers/sensors.py
aiohue/v2/models/__init__.py
aiohue/v2/models/behavior_instance.py
aiohue/v2/models/behavior_script.py
aiohue/v2/models/bell_button.py
aiohue/v2/models/bridge.py
aiohue/v2/models/bridge_home.py
aiohue/v2/models/button.py
aiohue/v2/models/camera_motion.py
aiohue/v2/models/contact.py
aiohue/v2/models/convenience_area_motion.py
aiohue/v2/models/device.py
aiohue/v2/models/device_power.py
aiohue/v2/models/entertainment.py
aiohue/v2/models/entertainment_configuration.py
aiohue/v2/models/feature.py
aiohue/v2/models/geofence_client.py
aiohue/v2/models/grouped_light.py
aiohue/v2/models/grouped_light_level.py
aiohue/v2/models/grouped_motion.py
aiohue/v2/models/homekit.py
aiohue/v2/models/light.py
aiohue/v2/models/light_level.py
aiohue/v2/models/matter.py
aiohue/v2/models/matter_fabric.py
aiohue/v2/models/motion.py
aiohue/v2/models/motion_area_configuration.py
aiohue/v2/models/relative_rotary.py
aiohue/v2/models/resource.py
aiohue/v2/models/room.py
aiohue/v2/models/scene.py
aiohue/v2/models/security_area_motion.py
aiohue/v2/models/service_group.py
aiohue/v2/models/smart_scene.py
aiohue/v2/models/tamper.py
aiohue/v2/models/temperature.py
aiohue/v2/models/zgp_connectivity.py
aiohue/v2/models/zigbee_connectivity.py
aiohue/v2/models/zone.py
aiohue-4.8.0.dist-info/licenses/LICENSE
aiohue-4.8.0.dist-info/METADATA
aiohue-4.8.0.dist-info/WHEEL
aiohue-4.8.0.dist-info/top_level.txt
aiohue-4.8.0.dist-info/RECORD
